ohmytofu/__init__.py
ohmytofu/placeholder.py
ohmytofu/_util/appdirs.py
ohmytofu/_util/constants.py
ohmytofu/_util/datetime.py
ohmytofu/_util/dev.py
ohmytofu/_util/docstring.py
ohmytofu/_util/dotenv.py
ohmytofu/_util/error.py
ohmytofu/_util/file.py
ohmytofu/_util/git.py
ohmytofu/_util/gqlclient.py
ohmytofu/_util/http.py
ohmytofu/_util/images.py
ohmytofu/_util/json.py
ohmytofu/_util/notebook.py
ohmytofu/_util/path.py
ohmytofu/_util/pattern.py
ohmytofu/_util/platform.py
ohmytofu/_util/queries.py
ohmytofu/_util/registry.py
ohmytofu/_util/retry.py
ohmytofu/_util/samples.py
ohmytofu/_util/text.py
ohmytofu/_util/url.py
ohmytofu/_util/version.py
ohmytofu/autobrew/trft/Subspace.py
ohmytofu/autobrew/trft/model.py
ohmytofu/autobrew/trft/resolvers.py
ohmytofu/autobrew/trft/trainer.py
ohmytofu/connectivity/gqlclient.py
ohmytofu/connectivity/sse.py
ohmytofu/connectivity/gql/queries.py
ohmytofu/display/__init__.py
ohmytofu/display/_display.py
ohmytofu/display/logger.py
ohmytofu/display/rich.py
ohmytofu/gql/queries.py
ohmytofu/log/__init__.py
ohmytofu/log/_file.py
ohmytofu/log/_log.py
ohmytofu/model/__init__.py
ohmytofu/model/_model.py
ohmytofu/model/_registry.py
ohmytofu/model/_tool.py
ohmytofu/model/_util.py
ohmytofu/ontology/dataobject.py
ohmytofu/util/__init__.py
ohmytofu/util/_context/__init__.py
ohmytofu/util/_context/concurrency.py
ohmytofu/util/_context/logger.py
ohmytofu/util/_context/resource.py
ohmytofu/util/_context/subprocess.py
ohmytofu/utils/runtime.py
tofu/autobrew/trft/__init__.py
tofu/autobrew/trft/model.py
ohmytofu-0.0.2.dist-info/LICENSE
ohmytofu-0.0.2.dist-info/METADATA
ohmytofu-0.0.2.dist-info/WHEEL
ohmytofu-0.0.2.dist-info/top_level.txt
ohmytofu-0.0.2.dist-info/RECORD
