Metadata-Version: 2.1
Name: ohmytofu
Version: 0.0.2
Summary: Client SDK to interface with the AI infrastructure at ohmytofu.ai
Author-email: Chris Krempel <hi@ohmytofu.ai>
Project-URL: Homepage, https://github.com/ohmytofu-ai/tofu-client-sdk
Project-URL: Issues, https://github.com/ohmytofu-ai/tofu-client-sdk/issues
Classifier: Programming Language :: Python :: 3
Classifier: License :: OSI Approved :: MIT License
Classifier: Operating System :: OS Independent
Requires-Python: >=3.8
License-File: LICENSE
Requires-Dist: inspect-ai
Requires-Dist: aiohttp-sse-client2
Requires-Dist: aiohttp
Requires-Dist: pandas
Requires-Dist: gql
Requires-Dist: rich
Requires-Dist: nest-asyncio
